{
  "install":{
    "profileName":"@project@-@version@",
    "target":"@project@-@version@",
    "path":"@artifact@",
    "version":"@project@ @version@",
    "filePath":"@universal_jar@",
    "welcome": "Welcome to the @project@ installer.",
    "minecraft":"@mcversion@",
    "mirrorList":"",
    "logo":"/installer-logo.png",
    "hideServer": true
  },
  "versionInfo": {
    "inheritsFrom": "@mcversion@",
    "id": "@project@-@version@",
    "time": "@timestamp@",
    "releaseTime": "2015-12-08T21:37:23+01:00",
    "type": "release",
    "arguments": {
      "game": [
        "--tweakClass",
        "@tweak_class@"
      ]
    },
    "mainClass": "net.minecraft.launchwrapper.Launch",
    "libraries": [
      {
        "name": "@artifact@"
      },
      {
        "name": "org.ow2.asm:asm-all:5.0.3"
      },
      {
        "name": "net.minecraft:launchwrapper:1.12"
      }
    ]
  }
}